hamming/__init__.py
hamming/framework.py
hamming/http_client.py
hamming/oai.py
hamming/tracing_helper.py
hamming/types.py
hamming/utils.py
hamming/callback/__init__.py
hamming/callback/langchain.py
hamming/resources/__init__.py
hamming/resources/api_resource.py
hamming/resources/datasets.py
hamming/resources/experiments.py
hamming/resources/logger.py
hamming/resources/monitoring.py
hamming/resources/prompts.py
hamming/resources/scoring.py
hamming/resources/tracing.py
hamming_sdk-0.0.17.dist-info/LICENSE
hamming_sdk-0.0.17.dist-info/METADATA
hamming_sdk-0.0.17.dist-info/WHEEL
hamming_sdk-0.0.17.dist-info/top_level.txt
hamming_sdk-0.0.17.dist-info/RECORD
