Metadata-Version: 2.1
Name: hamming-sdk
Version: 0.0.17
Summary: SDK for interacting with Hamming AI platform
Author-email: Hamming <contact@hamming.ai>
Project-URL: Homepage, https://github.com/pypa/sampleproject
Project-URL: Issues, https://github.com/pypa/sampleproject/issues
Classifier: Programming Language :: Python :: 3
Classifier: License :: OSI Approved :: MIT License
Classifier: Operating System :: OS Independent
Requires-Python: >=3.8
License-File: LICENSE
Requires-Dist: requests >=2.31.0
Requires-Dist: pydantic >=2.6.1
